pymydao/__init__.py
pymydao/db_helper.py
pymydao/model.py
pymydao-0.0.8.dist-info/METADATA
pymydao-0.0.8.dist-info/WHEEL
pymydao-0.0.8.dist-info/top_level.txt
pymydao-0.0.8.dist-info/RECORD
