Metadata-Version: 2.1
Name: pymydao
Version: 0.0.8
Summary: mysql dao
Home-page: https://github.com/taohuangtao/pymydao
Author: huangtao
Author-email: tao_huangtao@qq.com
License: MIT
Platform: UNKNOWN
Requires-Dist: pymysql
